Metadata-Version: 2.1
Name: odoo-addon-project_template_milestone
Version: 15.0.1.0.1
Summary: Adds function to copy of milestones when creating a project from template
Home-page: https://github.com/OCA/project
Author: Patrick Wilson, Odoo Community Association (OCA),Open Source Integrators
Author-email: support@odoo-community.org
License: AGPL-3
Classifier: Programming Language :: Python
Classifier: Framework :: Odoo
Classifier: Framework :: Odoo :: 15.0
Classifier: License :: OSI Approved :: GNU Affero General Public License v3
Classifier: Development Status :: 4 - Beta
Requires-Python: >=3.8
Requires-Dist: odoo-addon-project-task-milestone<15.1dev,>=15.0dev
Requires-Dist: odoo-addon-project-template<15.1dev,>=15.0dev
Requires-Dist: odoo<15.1dev,>=15.0a
